{
  "update": {
    "version_code": "61",
    "version_name": "2.7.0",
    "version_build": "0",
    "build_date": "22 октября 2022 г.",
    "links": [
      {
        "name": "AniLibria App",
        "url": "https://github.com/anilibria/anilibria-app/releases/download/2.7.0/AniLibria_v2.7.0.apk",
        "type": "file"
      },
      {
        "name": "AniLibria Lite (Белая иконка)",
        "url": "https://github.com/anilibria/anilibria-app/releases/download/2.7.0/AniLibria_Lite_v2.7.0.apk",
        "type": "file"
      }
    ],
    "important": [
      "Это одна из последних версий, в которой будет поддержка Android 4.4-5.1"
    ],
    "added": [
      "Возможность пропустить опенинг и ендинг в плеере",
      "Выборе темы приложения в зависимости от настроек в системе",
      "Выделение предпочтительных torrent раздач",
      "На экране релиза на ник войсера теперь перекидывает на экран команды проекта",
      "Описание для \"привязать устройство\"",
      "Вывод даты обновления в раздачах, сериях и в самом релизе"
    ],
    "fixed": [
      "Темная тема на экране обновления приложения",
      "Переход по ссылкам на странице команды ",
      "Новое сообщение в комментариях отображалось с белым фоном",
      "Определение часового пояса для вывода расписания",
      "Перед просмотром серии просило выбрать качество, независимо от сохраненных настроек"
    ],
    "changed": []
  }
}